eap/__init__.py
eap/eap.py
dsa_cat_module_python-0.0.0.dist-info/LICENSE
dsa_cat_module_python-0.0.0.dist-info/METADATA
dsa_cat_module_python-0.0.0.dist-info/WHEEL
dsa_cat_module_python-0.0.0.dist-info/top_level.txt
dsa_cat_module_python-0.0.0.dist-info/RECORD
