Metadata-Version: 2.2
Name: dsa_cat_module_python
Version: 0.0.0
Summary: This is a module for a wide variety of tasks.
Home-page: https://github.com/dsacat/dsa_cat_module_python/tree/main
Author: dsa_cat
Author-email: dsa.kirov@yandex.ru
License: MPL-2.0
Requires-Python: >=3.6
License-File: LICENSE
Dynamic: author
Dynamic: author-email
Dynamic: description
Dynamic: description-content-type
Dynamic: home-page
Dynamic: license
Dynamic: requires-python
Dynamic: summary
